CSC3050_P3/alu.v
module alu(
    input [31:0] instruction, 
    input [31:0] regA, 
    input [31:0] regB, 
    output reg [31:0] result, 
    output reg [2:0] flags
);

// task update_flags;
//     input [31:0] result;
//     input zero_flag_in;
//     input negative_flag_in;
//     input overflow_flag_in;
//     output reg zero_flag_out;
//     output reg negative_flag_out;
//     output reg overflow_flag_out;
// begin
//     zero_flag_out = zero_flag_in ? 1'b1 : result == 32'b0;
//     negative_flag_out = negative_flag_in ? 1'b1 : result[31];
//     overflow_flag_out = overflow_flag_in; // Overflow flag typically set during arithmetic operations
// end
// endtask

task update_flags;
    input [5:0] opcode;      // The opcode of the current instruction
    input [5:0] funct;       // The function field for R-type instructions
    input [31:0] result;     // The result of the computation
    input [31:0] regA;       // Value of the source register
    input [31:0] regB;       // Value of the target register or immediate value
    output reg zero_flag;    // The zero flag output
    output reg negative_flag;// The negative flag output
    output reg overflow_flag;// The overflow flag output
begin
    // Reset flags
    zero_flag = 0;
    negative_flag = 0;
    overflow_flag = 0;

    // Check for overflow flag conditions
    if ((opcode == 6'b000000 && funct == 6'b100000) || // add
        (opcode == 6'b001000) || // addi
        (opcode == 6'b000000 && funct == 6'b100010)) begin // sub
        // Overflow occurs if the signs of the inputs are the same and the sign of the result is different
        overflow_flag = ((regA[31] == regB[31]) && (result[31] != regA[31]));
    end

    // Check for zero flag conditions
    if (opcode == 6'b000100 || // beq
        opcode == 6'b000101) begin // bne
        zero_flag = (result == 0);
    end

    // Check for negative flag conditions
    if ((opcode == 6'b000000 && (funct == 6'b101010 || funct == 6'b101011)) || // slt, sltu
        (opcode == 6'b001010 || opcode == 6'b001011)) begin // slti, sltiu
        negative_flag = result[31];
    end
end
endtask



    wire [5:0] opcode;
    reg [5:0] funct;
    reg [4:0] rs, rt, rd, shamt;
    reg [15:0] immediate;
    reg [31:0] rs_reg, rt_reg;

    reg [31:0] temp_reg;
    reg zero, negative, overflow; // flags

    assign opcode = instruction[31:26];


    // parse instruction
    always @(*) begin
        // Extracting fields from the instruction
        funct = instruction[5:0];
        rs = instruction[25:21];
        rt = instruction[20:16];
        rd = instruction[15:11];
        shamt = instruction[10:6];
        immediate = instruction[15:0];

        // Sign-extend immediate for I-type instructions
        if (opcode == 6'b001000 || opcode == 6'b001100 || opcode == 6'b001101) begin
            immediate = {{16{instruction[15]}}, immediate};
        end
    end

    // execute different instructions
    always @(*) begin
        // todo: implement the instructions: add, addi, addu, addiu, sub, subu, and, andi, nor, or, ori, xor, xori, beq, bne, slt, slti, sltiu, sltu, lw, sw sll, sllv, srl, srlv, sra, srav
        // initialize flags
        zero = 0;
        negative = 0;
        overflow = 0;

        // add
        if (opcode == 6'b000000 && funct == 6'b100000) begin
            // fetch registers
            rs_reg = regA;
            rt_reg = regB;

            // perform addition
            temp_reg = rs_reg + rt_reg;
            $display("--add--%d = %d + %d", temp_reg, rs_reg, rt_reg);
        end

        // addi
        if (opcode == 6'b001000) begin
            // fetch registers
            rs_reg = regA;

            // perform addition
            temp_reg = rs_reg + immediate;
            $display("--addi--%d = %d + %d", temp_reg, rs_reg, immediate);
        end

        //addu
        if (opcode == 6'b000000 && funct == 6'b100001) begin
            // fetch registers
            rs_reg = regA;
            rt_reg = regB;

            // perform addition
            temp_reg = rs_reg + rt_reg;
            $display("--addu--%d = %d + %d", temp_reg, rs_reg, rt_reg);
        end

        //addiu
        if (opcode == 6'b001001) begin
            // fetch registers
            rs_reg = regA;

            // perform addition
            temp_reg = rs_reg + immediate;
            $display("--addiu--%d = %d + %d", temp_reg, rs_reg, immediate);
        end

        //sub
        if (opcode == 6'b000000 && funct == 6'b100010) begin
            // fetch registers
            rs_reg = regA;
            rt_reg = regB;

            // perform subtraction
            temp_reg = rs_reg - rt_reg;
            $display("--sub--%d = %d - %d", temp_reg, rs_reg, rt_reg);
        end

        //subu
        if (opcode == 6'b000000 && funct == 6'b100011) begin
            // fetch registers
            rs_reg = regA;
            rt_reg = regB;

            // perform subtraction
            temp_reg = rs_reg - rt_reg;
            $display("--subu--%d = %d - %d", temp_reg, rs_reg, rt_reg);
        end

        //and
        if (opcode == 6'b000000 && funct == 6'b100100) begin
            // fetch registers
            rs_reg = regA;
            rt_reg = regB;

            // perform and
            temp_reg = rs_reg & rt_reg;
            $display("--and--%d = %d & %d", temp_reg, rs_reg, rt_reg);
        end

        //andi
        if (opcode == 6'b001100) begin
            // fetch registers
            rs_reg = regA;

            // perform and
            temp_reg = rs_reg & immediate;
            $display("--andi--%d = %d & %d", temp_reg, rs_reg, immediate);
        end

        //nor
        if (opcode == 6'b000000 && funct == 6'b100111) begin
            // fetch registers
            rs_reg = regA;
            rt_reg = regB;

            // perform nor
            temp_reg = ~(rs_reg | rt_reg);
            $display("--nor--%d = ~(%d | %d)", temp_reg, rs_reg, rt_reg);
        end

        //or
        if (opcode == 6'b000000 && funct == 6'b100101) begin
            // fetch registers
            rs_reg = regA;
            rt_reg = regB;

            // perform or
            temp_reg = rs_reg | rt_reg;
            $display("--or--%d = %d | %d", temp_reg, rs_reg, rt_reg);
        end

        //ori
        if (opcode == 6'b001101) begin
            // fetch registers
            rs_reg = regA;

            // perform or
            temp_reg = rs_reg | immediate;
            $display("--ori--%d = %d | %d", temp_reg, rs_reg, immediate);
        end

        //xor
        if (opcode == 6'b000000 && funct == 6'b100110) begin
            // fetch registers
            rs_reg = regA;
            rt_reg = regB;

            // perform xor
            temp_reg = rs_reg ^ rt_reg;
            $display("--xor--%d = %d ^ %d", temp_reg, rs_reg, rt_reg);
        end

        //xori
        if (opcode == 6'b001110) begin
            // fetch registers
            rs_reg = regA;

            // perform xor
            temp_reg = rs_reg ^ immediate;
            $display("--xori--%d = %d ^ %d", temp_reg, rs_reg, immediate);
        end

        //beq
        if (opcode == 6'b000100) begin
            // fetch registers
            rs_reg = regA;
            rt_reg = regB;

            // perform beq
            if (rs_reg == rt_reg) begin
                temp_reg = immediate;
                $display("--beq--%d = %d", temp_reg, immediate);
            end
        end

        //bne
        if (opcode == 6'b000101) begin
            // fetch registers
            rs_reg = regA;
            rt_reg = regB;

            // perform bne
            if (rs_reg != rt_reg) begin
                temp_reg = immediate;
                $display("--bne--%d = %d", temp_reg, immediate);
            end
        end

        //slt
        if (opcode == 6'b000000 && funct == 6'b101010) begin
            // fetch registers
            rs_reg = regA;
            rt_reg = regB;

            // perform slt
            temp_reg = (rs_reg < rt_reg) ? 1 : 0;
            $display("--slt--%d = %d < %d", temp_reg, rs_reg, rt_reg);
        end

        //slti
        if (opcode == 6'b001010) begin
            // fetch registers
            rs_reg = regA;

            // perform slt
            temp_reg = (rs_reg < immediate) ? 1 : 0;
            $display("--slti--%d = %d < %d", temp_reg, rs_reg, immediate);
        end

        //sltiu
        if (opcode == 6'b001011) begin
            // fetch registers
            rs_reg = regA;

            // perform slt
            temp_reg = (rs_reg < immediate) ? 1 : 0;
            $display("--sltiu--%d = %d < %d", temp_reg, rs_reg, immediate);
        end

        //sltu
        if (opcode == 6'b000000 && funct == 6'b101011) begin
            // fetch registers
            rs_reg = regA;
            rt_reg = regB;

            // perform slt
            temp_reg = (rs_reg < rt_reg) ? 1 : 0;
            $display("--sltu--%d = %d < %d", temp_reg, rs_reg, rt_reg);
        end



        // update_flags(temp_reg, zero, negative, overflow, zero, negative, overflow);
        update_flags(opcode, funct, temp_reg, regA, regB, zero, negative, overflow);
    end

    // return result
    always @(*) begin
        result = temp_reg;
        flags = {zero, negative, overflow};
    end

endmodule

CSC3050_P3/test_alu.v
// `include "alu.v"

`timescale 1ns/1ps

module test_alu();
    reg [31:0] instruction, regA, regB;
    wire [31:0] result;
    wire [2:0] flags;  // Flags wire should be 3 bits to match the ALU module

    // Instantiate the ALU module
    alu test(
        .instruction(instruction),
        .regA(regA),
        .regB(regB),
        .result(result), 
        .flags(flags)
    );

    initial begin
        $dumpfile("test.vcd");
        $dumpvars(0, test_alu);

        $monitor("Time: %3d\n  Instruction: %32b\n  regA: %32b\n  regB: %32b\n  result: %32b\n  flags: Zero = %b, Negative = %b, Overflow = %b\nIn Decimals:\n  regA: %d\n  regB: %d\n  result: %d\n",
        $time, instruction, regA, regB, result, flags[2], flags[1], flags[0], regA, regB, result);

        // Test cases for each instruction

        // ADD (R-type)
        $display("Testing ADD...");
        instruction = {6'b000000, 5'd0, 5'd0, 5'd0, 5'd0, 6'b100000}; // R-type format for ADD
        regA = 32'h7FFFFFFF; // Largest positive 32-bit number
        regB = -1;
        #20;

        // ADDI (I-type)
        $display("Testing ADDI...");
        instruction = {6'b001000, 5'd0, 5'd0, 16'd5}; // I-type format for ADDI
        regA = 15;
        regB = 0; // regB is not used for ADDI
        #20;

        // ADDU (R-type)
        $display("Testing ADDU...");
        instruction = {6'b000000, 5'd0, 5'd0, 5'd0, 5'd0, 6'b100001}; // R-type format for ADDU
        regA = 1;
        regB = 32'hFFFFFFFE; // -2 in two's complement
        #20;

        // ADDIU (I-type)
        $display("Testing ADDIU...");
        instruction = {6'b001001, 5'd0, 5'd0, 16'hFFFF}; // I-type format for ADDIU
        regA = 32'h7FFFFFFF; // Largest positive 32-bit number
        #20;

        // SUB (R-type)
        $display("Testing SUB...");
        instruction = {6'b000000, 5'd0, 5'd0, 5'd0, 5'd0, 6'b100010}; // R-type format for SUB
        regA = 30;
        regB = -30;
        #20;

        // SUBU (R-type)
        $display("Testing SUBU...");
        instruction = {6'b000000, 5'd0, 5'd0, 5'd0, 5'd0, 6'b100011}; // R-type format for SUBU
        regA = 32'd10;
        regB = 32'd20;
        #20;

        // AND (R-type)
        $display("Testing AND...");
        instruction = {6'b000000, 5'd0, 5'd0, 5'd0, 5'd0, 6'b100100}; // R-type format for AND
        regA = 32'b1100;
        regB = 32'b1010;
        #20;

        // ANDI (I-type)
        $display("Testing ANDI...");
        instruction = {6'b001100, 5'd0, 5'd0, 16'b0000000000001100}; // I-type format for ANDI
        regA = 32'b1100;
        regB = 32'd0; // regB is not used for ANDI
        #20;

        // NOR (R-type)
        $display("Testing NOR...");
        instruction = {6'b000000, 5'd0, 5'd0, 5'd0, 5'd0, 6'b100111}; // R-type format for NOR
        regA = 32'b1100;
        regB = 32'b1010;
        #20;

        // OR (R-type)
        $display("Testing OR...");
        instruction = {6'b000000, 5'd0, 5'd0, 5'd0, 5'd0, 6'b100101}; // R-type format for OR
        regA = 32'b1100;
        regB = 32'b1010;
        #20;

        // ORI (I-type)
        $display("Testing ORI...");
        instruction = {6'b001101, 5'd0, 5'd0, 16'b0000000000001100}; // I-type format for ORI
        regA = 32'b1100;
        regB = 32'd0; // regB is not used for ORI
        #20;

        // XOR (R-type)
        $display("Testing XOR...");
        instruction = {6'b000000, 5'd0, 5'd0, 5'd0, 5'd0, 6'b100110}; // R-type format for XOR
        regA = 32'b1100;
        regB = 32'b1010;
        #20;

        // XORI (I-type)
        $display("Testing XORI...");
        instruction = {6'b001110, 5'd0, 5'd0, 16'b0000000000001100}; // I-type format for XORI
        regA = 32'b1100;
        regB = 32'd0; // regB is not used for XORI
        #20;

        // BEQ (I-type)
        $display("Testing BEQ...");
        instruction = {6'b000100, 5'd0, 5'd0, 16'b0000000000000010}; // I-type format for BEQ
        regA = 32'd10;
        regB = 32'd10;
        #20;

        // BNE (I-type)
        $display("Testing BNE...");
        instruction = {6'b000101, 5'd0, 5'd0, 16'b0000000000000010}; // I-type format for BNE
        regA = 32'd10;
        regB = 32'd20;
        #20;

        // SLT (R-type)
        $display("Testing SLT...");
        instruction = {6'b000000, 5'd0, 5'd0, 5'd0, 5'd0, 6'b101010}; // R-type format for SLT
        regA = 32'd10;
        regB = 32'd20;
        #20;

        // SLTI (I-type)
        $display("Testing SLTI...");
        instruction = {6'b001010, 5'd0, 5'd0, 16'b0000000000000010}; // I-type format for SLTI
        regA = 32'd5;
        regB = 32'd0; // regB is not used for SLTI
        #20;

        // SLTIU (I-type)
        $display("Testing SLTIU...");
        instruction = {6'b001011, 5'd0, 5'd0, 16'b0000000000000010}; // I-type format for SLTIU
        regA = 32'd20;
        regB = 32'd0; // regB is not used for SLTIU
        #20;

        // SLTU (R-type)
        $display("Testing SLTU...");
        instruction = {6'b000000, 5'd0, 5'd0, 5'd0, 5'd0, 6'b101011}; // R-type format for SLTU
        regA = 32'd10;
        regB = 32'd20;
        #20;

        // LW (I-type)
        $display("Testing LW...");
        instruction = {6'b100011, 5'd0, 5'd0, 16'b0000000000000010}; // I-type format for LW
        regA = 32'd0; // base register
        regB = 32'd0; // offset
        #20;

        // SW (I-type)
        $display("Testing SW...");
        instruction = {6'b101011, 5'd0, 5'd0, 16'b0000000000000010}; // I-type format for SW
        regA = 32'd0; // base register
        regB = 32'd10; // offset
        #20;

        // SLL (R-type)
        $display("Testing SLL...");
        instruction = {6'b000000, 5'd0, 5'd0, 5'd10, 5'd0, 6'b000000}; // R-type format for SLL
        regA = 32'd5;
        regB = 32'd0; // regB is not used for SLL
        #20;

        // SLLV (R-type)
        $display("Testing SLLV...");
        instruction = {6'b000000, 5'd0, 5'd0, 5'd2, 5'd0, 6'b000100}; // R-type format for SLLV
        regA = 32'd8;
        regB = 32'd0; // regB is not used for SLLV
        #20;

        // SRL (R-type)
        $display("Testing SRL...");
        instruction = {6'b000000, 5'd0, 5'd0, 5'd10, 5'd0, 6'b000010}; // R-type format for SRL
        regA = 32'd1024;
        regB = 32'd0; // regB is not used for SRL
        #20;

        // SRLV (R-type)
        $display("Testing SRLV...");
        instruction = {6'b000000, 5'd0, 5'd0, 5'd2, 5'd0, 6'b000110}; // R-type format for SRLV
        regA = 32'd1024;
        regB = 32'd0; // regB is not used for SRLV
        #20;

        // SRA (R-type)
        $display("Testing SRA...");
        instruction = {6'b000000, 5'd0, 5'd0, 5'd10, 5'd0, 6'b000011}; // R-type format for SRA
        regA = 32'hF0000000; // negative number
        regB = 32'd0; // regB is not used for SRA
        #20;

        // SRAV (R-type)
        $display("Testing SRAV...");
        instruction = {6'b000000, 5'd0, 5'd0, 5'd2, 5'd0, 6'b000111}; // R-type format for SRAV
        regA = 32'hF0000000; // negative number
        regB = 32'd0; // regB is not used for SRAV
        #20;

        // Complete the test
        $finish;
    end
endmodule

CSC3050_P3/test.vcd
$date
	Tue Nov  7 02:07:42 2023
$end
$version
	Icarus Verilog
$end
$timescale
	1ps
$end
$scope module test_alu $end
$var wire 32 ! result [31:0] $end
$var wire 3 " flags [2:0] $end
$var reg 32 # instruction [31:0] $end
$var reg 32 $ regA [31:0] $end
$var reg 32 % regB [31:0] $end
$scope module test $end
$var wire 32 & instruction [31:0] $end
$var wire 32 ' regA [31:0] $end
$var wire 32 ( regB [31:0] $end
$var wire 6 ) opcode [5:0] $end
$var reg 3 * flags [2:0] $end
$var reg 6 + funct [5:0] $end
$var reg 16 , immediate [15:0] $end
$var reg 1 - negative $end
$var reg 1 . overflow $end
$var reg 5 / rd [4:0] $end
$var reg 32 0 result [31:0] $end
$var reg 5 1 rs [4:0] $end
$var reg 32 2 rs_reg [31:0] $end
$var reg 5 3 rt [4:0] $end
$var reg 32 4 rt_reg [31:0] $end
$var reg 5 5 shamt [4:0] $end
$var reg 32 6 temp_reg [31:0] $end
$var reg 1 7 zero $end
$scope task update_flags $end
$var reg 6 8 funct [5:0] $end
$var reg 1 9 negative_flag $end
$var reg 6 : opcode [5:0] $end
$var reg 1 ; overflow_flag $end
$var reg 32 < regA [31:0] $end
$var reg 32 = regB [31:0] $end
$var reg 32 > result [31:0] $end
$var reg 1 ? zero_flag $end
$upscope $end
$upscope $end
$upscope $end
$enddefinitions $end
$comment Show the parameter values. $end
$dumpall
$end
#0
$dumpvars
0?
b1111111111111111111111111111110 >
b11111111111111111111111111111111 =
b1111111111111111111111111111111 <
0;
b0 :
09
b100000 8
07
b1111111111111111111111111111110 6
b0 5
b11111111111111111111111111111111 4
b0 3
b1111111111111111111111111111111 2
b0 1
b1111111111111111111111111111110 0
b0 /
0.
0-
b100000 ,
b100000 +
b0 *
b0 )
b11111111111111111111111111111111 (
b1111111111111111111111111111111 '
b100000 &
b11111111111111111111111111111111 %
b1111111111111111111111111111111 $
b100000 #
b0 "
b1111111111111111111111111111110 !
$end
#20000
b10100 !
b10100 0
b0 =
b1111 <
b10100 >
b101 8
b1000 :
b10100 6
b1111 2
b101 ,
b101 +
b1000 )
b0 %
b0 (
b1111 $
b1111 '
b100000000000000000000000000101 #
b100000000000000000000000000101 &
#40000
b11111111111111111111111111111111 !
b11111111111111111111111111111111 0
b11111111111111111111111111111110 =
b1 <
b11111111111111111111111111111111 >
b100001 8
b0 :
b11111111111111111111111111111111 6
b11111111111111111111111111111110 4
b1 2
b100001 ,
b100001 +
b0 )
b11111111111111111111111111111110 %
b11111111111111111111111111111110 (
b1 $
b1 '
b100001 #
b100001 &
#60000
b10000000000000001111111111111110 !
b10000000000000001111111111111110 0
b1111111111111111111111111111111 <
b10000000000000001111111111111110 >
b111111 8
b1001 :
b10000000000000001111111111111110 6
b1111111111111111111111111111111 2
b1111111111111111 ,
b11111 5
b11111 /
b111111 +
b1001 )
b1111111111111111111111111111111 $
b1111111111111111111111111111111 '
b100100000000001111111111111111 #
b100100000000001111111111111111 &
#80000
b111100 !
b111100 0
b11111111111111111111111111100010 =
b11110 <
b111100 >
b100010 8
b0 :
b111100 6
b11111111111111111111111111100010 4
b11110 2
b100010 ,
b0 5
b0 /
b100010 +
b0 )
b11111111111111111111111111100010 %
b11111111111111111111111111100010 (
b11110 $
b11110 '
b100010 #
b100010 &
#100000
b11111111111111111111111111110110 !
b11111111111111111111111111110110 0
b10100 =
b1010 <
b11111111111111111111111111110110 >
b100011 8
b11111111111111111111111111110110 6
b10100 4
b1010 2
b100011 ,
b100011 +
b10100 %
b10100 (
b1010 $
b1010 '
b100011 #
b100011 &
#120000
b1000 !
b1000 0
b1010 =
b1100 <
b1000 >
b100100 8
b1000 6
b1010 4
b1100 2
b100100 ,
b100100 +
b1010 %
b1010 (
b1100 $
b1100 '
b100100 #
b100100 &
#140000
b1100 !
b1100 0
b0 =
b1100 >
b1100 8
b1100 :
b1100 6
b1100 ,
b1100 +
b1100 )
b0 %
b0 (
b110000000000000000000000001100 #
b110000000000000000000000001100 &
#160000
b11111111111111111111111111110001 !
b11111111111111111111111111110001 0
b1010 =
b11111111111111111111111111110001 >
b100111 8
b0 :
b11111111111111111111111111110001 6
b100111 ,
b100111 +
b0 )
b1010 %
b1010 (
b100111 #
b100111 &
#180000
b1110 !
b1110 0
b1110 >
b100101 8
b1110 6
b100101 ,
b100101 +
b100101 #
b100101 &
#200000
b1100 !
b1100 0
b0 =
b1100 >
b1100 8
b1101 :
b1100 6
b1100 ,
b1100 +
b1101 )
b0 %
b0 (
b110100000000000000000000001100 #
b110100000000000000000000001100 &
#220000
b110 !
b110 0
b1010 =
b110 >
b100110 8
b0 :
b110 6
b100110 ,
b100110 +
b0 )
b1010 %
b1010 (
b100110 #
b100110 &
#240000
b0 !
b0 0
b0 =
b0 >
b1100 8
b1110 :
b0 6
b1100 ,
b1100 +
b1110 )
b0 %
b0 (
b111000000000000000000000001100 #
b111000000000000000000000001100 &
#260000
b10 !
b10 0
b1010 =
b1010 <
b10 >
b10 8
b100 :
b10 6
b1010 2
b10 ,
b10 +
b100 )
b1010 %
b1010 (
b1010 $
b1010 '
b10000000000000000000000000010 #
b10000000000000000000000000010 &
#280000
b10100 =
b101 :
b10100 4
b101 )
b10100 %
b10100 (
b10100000000000000000000000010 #
b10100000000000000000000000010 &
#300000
b1 !
b1 0
b1 >
b101010 8
b0 :
b1 6
b101010 ,
b101010 +
b0 )
b101010 #
b101010 &
#320000
b0 !
b0 0
b0 =
b101 <
b0 >
b10 8
b1010 :
b0 6
b101 2
b10 ,
b10 +
b1010 )
b0 %
b0 (
b101 $
b101 '
b101000000000000000000000000010 #
b101000000000000000000000000010 &
#340000
b10100 <
b1011 :
b10100 2
b1011 )
b10100 $
b10100 '
b101100000000000000000000000010 #
b101100000000000000000000000010 &
#360000
b1 !
b1 0
b10100 =
b1010 <
b1 >
b101011 8
b0 :
b1 6
b1010 2
b101011 ,
b101011 +
b0 )
b10100 %
b10100 (
b1010 $
b1010 '
b101011 #
b101011 &
#380000
b0 =
b0 <
b10 8
b100011 :
b10 ,
b10 +
b100011 )
b0 %
b0 (
b0 $
b0 '
b10001100000000000000000000000010 #
b10001100000000000000000000000010 &
#400000
b1010 =
b101011 :
b101011 )
b1010 %
b1010 (
b10101100000000000000000000000010 #
b10101100000000000000000000000010 &
#420000
b0 =
b101 <
b0 8
b0 :
b101000000000000 ,
b1010 /
b0 +
b0 )
b0 %
b0 (
b101 $
b101 '
b101000000000000 #
b101000000000000 &
#440000
b1000 <
b100 8
b1000000000100 ,
b10 /
b100 +
b1000 $
b1000 '
b1000000000100 #
b1000000000100 &
#460000
b10000000000 <
b10 8
b101000000000010 ,
b1010 /
b10 +
b10000000000 $
b10000000000 '
b101000000000010 #
b101000000000010 &
#480000
b110 8
b1000000000110 ,
b10 /
b110 +
b1000000000110 #
b1000000000110 &
#500000
b11110000000000000000000000000000 <
b11 8
b101000000000011 ,
b1010 /
b11 +
b11110000000000000000000000000000 $
b11110000000000000000000000000000 '
b101000000000011 #
b101000000000011 &
#520000
b111 8
b1000000000111 ,
b10 /
b111 +
b1000000000111 #
b1000000000111 &
